trend_intelligence/Dashboard.py
trend_intelligence/Prediction.py
trend_intelligence/Recommendation.py
trend_intelligence/__init__.py
aiops4b_NTTDataUK-0.9.dist-info/LICENSE.txt
aiops4b_NTTDataUK-0.9.dist-info/METADATA
aiops4b_NTTDataUK-0.9.dist-info/WHEEL
aiops4b_NTTDataUK-0.9.dist-info/top_level.txt
aiops4b_NTTDataUK-0.9.dist-info/RECORD
