Metadata-Version: 2.1
Name: aiops4b-NTTDataUK
Version: 0.9
Summary: Trend analysis and sales forecast
Home-page: UNKNOWN
Author: Julian Gonzalez Galvez
Author-email: julian.gonzalez.galvez@gmail.com
License: UNKNOWN
Platform: UNKNOWN
Classifier: Programming Language :: Python :: 3
Classifier: License :: OSI Approved :: MIT License
Classifier: Operating System :: OS Independent
Requires-Python: >=3.6
License-File: LICENSE.txt
